treco/__init__.py
treco/core.py
treco/extras.py
treco/forecasts.py
treco/indicators.py
treco/markets.py
treco/requirements.txt
treco-0.0.1.dist-info/WHEEL
treco-0.0.1.dist-info/METADATA
treco-0.0.1.dist-info/RECORD
